PyHGNC-0.2.4.dist-info/DESCRIPTION.rst
PyHGNC-0.2.4.dist-info/METADATA
PyHGNC-0.2.4.dist-info/RECORD
PyHGNC-0.2.4.dist-info/WHEEL
PyHGNC-0.2.4.dist-info/entry_points.txt
PyHGNC-0.2.4.dist-info/metadata.json
PyHGNC-0.2.4.dist-info/top_level.txt
pyhgnc/__init__.py
pyhgnc/__main__.py
pyhgnc/cli.py
pyhgnc/constants.py
pyhgnc/manager/__init__.py
pyhgnc/manager/database.py
pyhgnc/manager/defaults.py
pyhgnc/manager/make_json_serializable.py
pyhgnc/manager/models.py
pyhgnc/manager/query.py
pyhgnc/webserver/__init__.py
pyhgnc/webserver/web.py
pyhgnc/webserver/static/images/aetionomy_logo.png
pyhgnc/webserver/static/images/imi_logo.png
pyhgnc/webserver/static/images/phago_logo.jpeg
pyhgnc/webserver/static/images/project_logo.png
pyhgnc/webserver/static/images/scai_logo.png
pyhgnc/webserver/templates/about.html
pyhgnc/webserver/templates/dashboard.html
pyhgnc/webserver/templates/home.html
pyhgnc/webserver/templates/layout.html
pyhgnc/webserver/templates/login.html
pyhgnc/webserver/templates/register.html
pyhgnc/webserver/templates/includes/_formhelpers.html
pyhgnc/webserver/templates/includes/_messages.html
pyhgnc/webserver/templates/includes/_navbar.html
