Metadata-Version: 2.0
Name: PyHGNC
Version: 0.2.4
Summary: Importing and querying HGNC data
Home-page: https://github.com/LeKono/pyhgnc.git
Author: Andrej Konotopez
Author-email: Andrej.Konotopez@scai.fraunhofer.de
License: Apache 2.0 License
Keywords: HGNC,gene names,Bioinformatics
Platform: UNKNOWN
Classifier: Development Status :: 5 - Production/Stable
Classifier: Operating System :: OS Independent
Classifier: Environment :: Console
Classifier: Programming Language :: Python
Classifier: Programming Language :: Python :: 2.7
Classifier: Programming Language :: Python :: 3.4
Classifier: Programming Language :: Python :: 3.5
Classifier: Programming Language :: Python :: 3.6
Classifier: Intended Audience :: Developers
Classifier: License :: OSI Approved :: MIT License
Classifier: Topic :: Database
Classifier: Topic :: Scientific/Engineering :: Bio-Informatics
Requires-Dist: click
Requires-Dist: configparser
Requires-Dist: flasgger
Requires-Dist: flask
Requires-Dist: flask-cors
Requires-Dist: pandas
Requires-Dist: passlib
Requires-Dist: pymysql
Requires-Dist: sqlalchemy
Requires-Dist: tqdm
Requires-Dist: wtforms
